{
  "key": "plugin_content_manager_configuration_content_types::api::assorted-table.assorted-table",
  "value": {
    "settings": {
      "bulkable": true,
      "filterable": true,
      "searchable": true,
      "pageSize": 10,
      "mainField": "tableName",
      "defaultSortBy": "id",
      "defaultSortOrder": "ASC"
    },
    "metadatas": {
      "id": {
        "edit": {},
        "list": {
          "label": "id",
          "searchable": true,
          "sortable": true
        }
      },
      "header": {
        "edit": {
          "label": "Header",
          "description": "",
          "placeholder": "",
          "visible": true,
          "editable": true
        },
        "list": {
          "label": "Header",
          "searchable": false,
          "sortable": false
        }
      },
      "table": {
        "edit": {
          "label": "Table",
          "description": "",
          "placeholder": "",
          "visible": true,
          "editable": true
        },
        "list": {
          "label": "Table",
          "searchable": false,
          "sortable": false
        }
      },
      "tableName": {
        "edit": {
          "label": "Table Name",
          "description": "",
          "placeholder": "",
          "visible": true,
          "editable": true
        },
        "list": {
          "label": "Table Name",
          "searchable": true,
          "sortable": true
        }
      },
      "hideHeader": {
        "edit": {
          "label": "Hide Header",
          "description": "",
          "placeholder": "",
          "visible": true,
          "editable": true
        },
        "list": {
          "label": "Hide Header",
          "searchable": true,
          "sortable": true
        }
      },
      "createdAt": {
        "edit": {
          "label": "createdAt",
          "description": "",
          "placeholder": "",
          "visible": false,
          "editable": true
        },
        "list": {
          "label": "createdAt",
          "searchable": true,
          "sortable": true
        }
      },
      "updatedAt": {
        "edit": {
          "label": "updatedAt",
          "description": "",
          "placeholder": "",
          "visible": false,
          "editable": true
        },
        "list": {
          "label": "updatedAt",
          "searchable": true,
          "sortable": true
        }
      },
      "createdBy": {
        "edit": {
          "label": "createdBy",
          "description": "",
          "placeholder": "",
          "visible": false,
          "editable": true,
          "mainField": "firstname"
        },
        "list": {
          "label": "createdBy",
          "searchable": true,
          "sortable": true
        }
      },
      "updatedBy": {
        "edit": {
          "label": "updatedBy",
          "description": "",
          "placeholder": "",
          "visible": false,
          "editable": true,
          "mainField": "firstname"
        },
        "list": {
          "label": "updatedBy",
          "searchable": true,
          "sortable": true
        }
      }
    },
    "layouts": {
      "list": [
        "id",
        "createdAt",
        "updatedAt",
        "tableName"
      ],
      "edit": [
        [
          {
            "name": "tableName",
            "size": 6
          }
        ],
        [
          {
            "name": "header",
            "size": 12
          }
        ],
        [
          {
            "name": "hideHeader",
            "size": 4
          }
        ],
        [
          {
            "name": "table",
            "size": 12
          }
        ]
      ]
    },
    "uid": "api::assorted-table.assorted-table"
  },
  "type": "object",
  "environment": null,
  "tag": null
}